[
  {
    "id": "nt_90",
    "title": "Novo Testamento em 90 Dias",
    "description": "Leia todo o Novo Testamento em 3 meses.",
    "isPremium": false,
    "filename": "nt_90.json"
  },
  {
    "id": "salmos",
    "title": "Salmos e Provérbios",
    "description": "Sabedoria diária para sua vida.",
    "isPremium": false,
    "filename": "salmos.json"
  },
  {
    "id": "anual",
    "title": "Bíblia em 1 Ano",
    "description": "O plano completo de Gênesis a Apocalipse.",
    "isPremium": true,
    "filename": "anual.json"
  }
]
